Metadata-Version: 2.1
Name: odoo14-addon-account_reconciliation_widget
Version: 14.0.2.0.8
Summary: Account reconciliation widget
Home-page: https://github.com/OCA/account-reconcile
Author: Odoo, Ozono Multimedia, Odoo Community Association (OCA)
Author-email: support@odoo-community.org
License: AGPL-3
Classifier: Programming Language :: Python
Classifier: Framework :: Odoo
Classifier: Framework :: Odoo :: 14.0
Classifier: License :: OSI Approved :: GNU Affero General Public License v3
Requires-Python: >=3.6
Requires-Dist: odoo <14.1dev,>=14.0a
